LICENSE
MANIFEST.in
README.md
runtests.py
setup.py
djangorestframework_gis_distance.egg-info/PKG-INFO
djangorestframework_gis_distance.egg-info/SOURCES.txt
djangorestframework_gis_distance.egg-info/dependency_links.txt
djangorestframework_gis_distance.egg-info/not-zip-safe
djangorestframework_gis_distance.egg-info/requires.txt
djangorestframework_gis_distance.egg-info/top_level.txt
requirements/install.txt
requirements/tests.txt
rest_framework_gis_distance/__init__.py
rest_framework_gis_distance/fields.py
rest_framework_gis_distance/filters.py