Metadata-Version: 1.1
Name: djangorestframework-gis-distance
Version: 1.0.0
Summary: UNKNOWN
Home-page: https://github.com/Frojd/restframework-gis-distance
Author: Fröjd
Author-email: martin@marteinn.se
License: MIT
Platform: UNKNOWN
Classifier: Development Status :: 4 - Beta
Classifier: Environment :: Web Environment
Classifier: Intended Audience :: Developers
Classifier: Natural Language :: English
Classifier: Intended Audience :: Developers
Classifier: License :: OSI Approved :: MIT License
Classifier: Programming Language :: Python
Classifier: Programming Language :: Python :: 2
Classifier: Programming Language :: Python :: 2.7
Classifier: Framework :: Django
Classifier: Topic :: Utilities
